diskcache_decorator/__init__.py
diskcache_decorator-0.2.0.dist-info/LICENSE
diskcache_decorator-0.2.0.dist-info/METADATA
diskcache_decorator-0.2.0.dist-info/WHEEL
diskcache_decorator-0.2.0.dist-info/top_level.txt
diskcache_decorator-0.2.0.dist-info/RECORD
