Metadata-Version: 2.2
Name: diskcache-decorator
Version: 0.2.0
Summary: function decorator that caches results to disk
Maintainer: Jacob Brunson
License: Apache-2.0
Project-URL: Repository, https://github.com/pearmaster/diskcache-decorator
Requires-Python: >=3.10
License-File: LICENSE
Requires-Dist: diskcache>=5.6.3
